sharedstreets/__init__.py
sharedstreets/read.py
sharedstreets/sharedstreets_pb2.py
sharedstreets/tile.py
sharedstreets/webapp.py
sharedstreets/dataframe/__init__.py
sharedstreets/tests/__init__.py
sharedstreets/tests/test_dataframe.py
sharedstreets/tests/test_tile.py
sharedstreets/tests/data/20180307-geometry.pbf
sharedstreets/tests/data/20180307-intersection.pbf
sharedstreets/tests/data/20180307-metadata.pbf
sharedstreets/tests/data/20180307-reference.pbf
sharedstreets/tests/data/20180312-geometry.pbf
sharedstreets/tests/data/20180312-intersection.pbf
sharedstreets/tests/data/20180312-metadata.pbf
sharedstreets/tests/data/20180312-reference.pbf
sharedstreets/tests/data/http404-intersection.pbf
sharedstreets-0.6.0.dist-info/LICENSE
sharedstreets-0.6.0.dist-info/METADATA
sharedstreets-0.6.0.dist-info/WHEEL
sharedstreets-0.6.0.dist-info/entry_points.txt
sharedstreets-0.6.0.dist-info/top_level.txt
sharedstreets-0.6.0.dist-info/RECORD
